gemini_cli/__init__.py
gemini_cli/config.py
gemini_cli/main.py
gemini_cli/utils.py
gemini_cli/models/__init__.py
gemini_cli/models/gemini.py
gemini_cli/models/openrouter.py
gemini_cli/tools/__init__.py
gemini_cli/tools/base.py
gemini_cli/tools/directory_tools.py
gemini_cli/tools/file_tools.py
gemini_cli/tools/quality_tools.py
gemini_cli/tools/summarizer_tool.py
gemini_cli/tools/system_tools.py
gemini_cli/tools/task_complete_tool.py
gemini_cli/tools/test_runner.py
gemini_cli/tools/tree_tool.py
code_lm-0.2.5.dist-info/METADATA
code_lm-0.2.5.dist-info/WHEEL
code_lm-0.2.5.dist-info/entry_points.txt
code_lm-0.2.5.dist-info/top_level.txt
code_lm-0.2.5.dist-info/RECORD
