Metadata-Version: 2.2
Name: code-lm
Version: 0.2.5
Summary: An AI coding assistant using various LLM models.
Home-page: https://github.com/Panagiotis897/lm-code
Author: Panagiotis897
Author-email: Panagiotis897 <orion256business@gmail.com>
Project-URL: Homepage, https://github.com/Panagiotis897/lm-code
Project-URL: Bug Tracker, https://github.com/Panagiotis897/lm-code/issues
Classifier: Programming Language :: Python :: 3
Classifier: Operating System :: OS Independent
Classifier: Development Status :: 3 - Alpha
Classifier: Environment :: Console
Classifier: Intended Audience :: Developers
Classifier: Topic :: Software Development
Classifier: Topic :: Utilities
Requires-Python: >=3.7
Requires-Dist: click>=8.0
Requires-Dist: rich>=13.0
Requires-Dist: requests>=2.25.0
Requires-Dist: PyYAML>=6.0
Requires-Dist: tiktoken>=0.6.0
Requires-Dist: questionary>=2.0.0
Dynamic: author
Dynamic: home-page
Dynamic: requires-python
